LICENSE
MANIFEST.in
README.rst
setup.py
docs/conf.py
pulpo_forms/JSONSerializers.py
pulpo_forms/__init__.py
pulpo_forms/admin.py
pulpo_forms/auth.py
pulpo_forms/cms_plugins.py
pulpo_forms/fields.py
pulpo_forms/middlets.py
pulpo_forms/models.py
pulpo_forms/permissions.py
pulpo_forms/serializers.py
pulpo_forms/signals.py
pulpo_forms/urls.py
pulpo_forms/views.py
pulpo_forms.egg-info/PKG-INFO
pulpo_forms.egg-info/SOURCES.txt
pulpo_forms.egg-info/dependency_links.txt
pulpo_forms.egg-info/pbr.json
pulpo_forms.egg-info/requires.txt
pulpo_forms.egg-info/top_level.txt
pulpo_forms.egg-info/zip-safe
pulpo_forms/fieldtypes/CIField.py
pulpo_forms/fieldtypes/CheckboxField.py
pulpo_forms/fieldtypes/EmailField.py
pulpo_forms/fieldtypes/Field.py
pulpo_forms/fieldtypes/FieldFactory.py
pulpo_forms/fieldtypes/FileField.py
pulpo_forms/fieldtypes/GeoField.py
pulpo_forms/fieldtypes/ListField.py
pulpo_forms/fieldtypes/ModelField.py
pulpo_forms/fieldtypes/NumberField.py
pulpo_forms/fieldtypes/SelectField.py
pulpo_forms/fieldtypes/TextAreaField.py
pulpo_forms/fieldtypes/TextField.py
pulpo_forms/fieldtypes/__init__.py
pulpo_forms/fieldtypes/field_type.py
pulpo_forms/migrations/0001_initial.py
pulpo_forms/migrations/__init__.py
pulpo_forms/static/__init__.py
pulpo_forms/static/angular/FileSaver.js
pulpo_forms/static/angular/__init__.py
pulpo_forms/static/angular/angular-charts.js
pulpo_forms/static/angular/angular-charts.min.js
pulpo_forms/static/angular/angular-file-upload-shim.js
pulpo_forms/static/angular/angular-file-upload.js
pulpo_forms/static/angular/angular-growl-notifications.min.js
pulpo_forms/static/angular/angular-load.min.js
pulpo_forms/static/angular/angular-mocks.js
pulpo_forms/static/angular/angular-resource.min.js
pulpo_forms/static/angular/angular-resource.min.js.map
pulpo_forms/static/angular/angular-route.min.js
pulpo_forms/static/angular/angular-sanitize.js
pulpo_forms/static/angular/angular.js
pulpo_forms/static/angular/angular.min.js
pulpo_forms/static/angular/angular.min.js.map
pulpo_forms/static/angular/bluebird.js
pulpo_forms/static/angular/captcha.js
pulpo_forms/static/angular/checklist-model.js
pulpo_forms/static/angular/d3.js
pulpo_forms/static/angular/d3.min.js
