Metadata-Version: 1.1
Name: pulpo-forms
Version: 1.1
Summary: Django App to create dynamic Surveys
Home-page: https://github.com/pulpocoders/pulpo-forms-django
Author: PythonWarriors + Pulpocoders
Author-email: info@trea.uy
License: Apache License
Keywords: Django Survey Framework
Platform: UNKNOWN
Classifier: Programming Language :: Python
Classifier: Programming Language :: Python :: 3.4
Classifier: License :: OSI Approved :: Apache Software License
Classifier: Operating System :: OS Independent
Classifier: Development Status :: 4 - Beta
Classifier: Environment :: Web Environment
Classifier: Intended Audience :: Information Technology
Classifier: Topic :: Internet :: WWW/HTTP :: WSGI :: Application
